mdgt/__init__.py
mdgt/__main__.py
mdgt/mdgt.py
mdgt/provider.py
mdgt/webserve.py
mdgt/providers/actor.json
mdgt/providers/movie.json
mdgt/providers/stock.json
mdgt/providers/wp.json
mdgt-0.1.0.dist-info/DESCRIPTION.rst
mdgt-0.1.0.dist-info/METADATA
mdgt-0.1.0.dist-info/RECORD
mdgt-0.1.0.dist-info/WHEEL
mdgt-0.1.0.dist-info/metadata.json
mdgt-0.1.0.dist-info/top_level.txt
