Metadata-Version: 2.0
Name: mdgt
Version: 0.1.0
Summary: Microdata-Parsing Microservice
Home-page: https://github.com/jjcamp/mdgt
Author: John Camp and Contributors
Author-email: UNKNOWN
License: MIT
Keywords: microdata
Platform: UNKNOWN
Requires-Dist: lxml (>=3.5.0)
Requires-Dist: requests (>=2.9.1)
